LICENSE
MANIFEST.in
README.md
setup.py
conda_deps/__init__.py
conda_deps/conda_deps.py
conda_deps/python_deps.json
conda_deps/r_deps.json
conda_deps.egg-info/PKG-INFO
conda_deps.egg-info/SOURCES.txt
conda_deps.egg-info/dependency_links.txt
conda_deps.egg-info/entry_points.txt
conda_deps.egg-info/top_level.txt