Metadata-Version: 2.1
Name: conda-deps
Version: 0.0.8
Summary: Generate conda environment files from Python source code
Home-page: https://github.com/cgat-developers/conda-deps
Author: cgat-developers
Author-email: sebastian.luna.valero@gmail.com
License: UNKNOWN
Platform: UNKNOWN
Classifier: Programming Language :: Python :: 3
Classifier: License :: OSI Approved :: MIT License
Classifier: Operating System :: OS Independent
